self_healing_localization-0.1.5.dist-info/licenses/LICENSE
shl/__init__.py
shl/engine/__init__.py
shl/engine/ai_translation.py
shl/engine/core.py
shl/engine/localizer.py
shl/engine/template_localizer.py
self_healing_localization-0.1.5.dist-info/METADATA
self_healing_localization-0.1.5.dist-info/WHEEL
self_healing_localization-0.1.5.dist-info/top_level.txt
self_healing_localization-0.1.5.dist-info/RECORD
