Metadata-Version: 2.4
Name: self-healing-localization
Version: 0.1.5
Summary: A self-healing localization layer for Python applications, automatically creating missing language files and keys.
Author: Tuomas Lähteenmäki
License: MIT License
Project-URL: Homepage, https://codeberg.org/lahtis/Self_Healing_Localization
Project-URL: Repository, https://codeberg.org/lahtis/Self_Healing_Localization
Project-URL: Issues, https://codeberg.org/lahtis/Self_Healing_Localization/issues
Keywords: localization,i18n,internationalization,translation,templates,self-healing,automation,python
Classifier: Development Status :: 3 - Alpha
Classifier: License :: OSI Approved :: MIT License
Classifier: Programming Language :: Python :: 3
Classifier: Programming Language :: Python :: 3.8
Classifier: Programming Language :: Python :: 3.9
Classifier: Programming Language :: Python :: 3.10
Classifier: Programming Language :: Python :: 3.11
Classifier: Intended Audience :: Developers
Classifier: Topic :: Software Development :: Internationalization
Classifier: Topic :: Software Development :: Libraries
Requires-Python: >=3.8
License-File: LICENSE
Dynamic: license-file
